{
  "main": {
    "id": "7d62aebba34e7608",
    "type": "split",
    "children": [
      {
        "id": "dbbfa171d055b0f4",
        "type": "tabs",
        "children": [
          {
            "id": "7e23daa8b7702666",
            "type": "leaf",
            "state": {
              "type": "markdown",
              "state": {
                "file": "编译Qt5.15.12.md",
                "mode": "source",
                "source": false
              }
            }
          }
        ]
      }
    ],
    "direction": "vertical"
  },
  "left": {
    "id": "10fb7f184b7e041c",
    "type": "split",
    "children": [
      {
        "id": "b0e498ab6fd31168",
        "type": "tabs",
        "children": [
          {
            "id": "1230c15a08d56382",
            "type": "leaf",
            "state": {
              "type": "file-explorer",
              "state": {
                "sortOrder": "alphabetical"
              }
            }
          },
          {
            "id": "0d635b4b649fcd1c",
            "type": "leaf",
            "state": {
              "type": "search",
              "state": {
                "query": "",
                "matchingCase": false,
                "explainSearch": false,
                "collapseAll": false,
                "extraContext": false,
                "sortOrder": "alphabetical"
              }
            }
          },
          {
            "id": "e978c3274e0f2854",
            "type": "leaf",
            "state": {
              "type": "bookmarks",
              "state": {}
            }
          }
        ]
      }
    ],
    "direction": "horizontal",
    "width": 300
  },
  "right": {
    "id": "fcdeee5c1be1338a",
    "type": "split",
    "children": [
      {
        "id": "568f0063d5955a69",
        "type": "tabs",
        "children": [
          {
            "id": "d108a1ef260583b8",
            "type": "leaf",
            "state": {
              "type": "backlink",
              "state": {
                "file": "编译Qt5.15.12.md",
                "collapseAll": false,
                "extraContext": false,
                "sortOrder": "alphabetical",
                "showSearch": false,
                "searchQuery": "",
                "backlinkCollapsed": false,
                "unlinkedCollapsed": true
              }
            }
          },
          {
            "id": "91f9a3848344908a",
            "type": "leaf",
            "state": {
              "type": "outgoing-link",
              "state": {
                "file": "编译Qt5.15.12.md",
                "linksCollapsed": false,
                "unlinkedCollapsed": true
              }
            }
          },
          {
            "id": "440baac5b4ce80ff",
            "type": "leaf",
            "state": {
              "type": "tag",
              "state": {
                "sortOrder": "frequency",
                "useHierarchy": true
              }
            }
          },
          {
            "id": "b8435c57bea1ad12",
            "type": "leaf",
            "state": {
              "type": "outline",
              "state": {
                "file": "编译Qt5.15.12.md"
              }
            }
          }
        ],
        "currentTab": 3
      }
    ],
    "direction": "horizontal",
    "width": 300,
    "collapsed": true
  },
  "left-ribbon": {
    "hiddenItems": {
      "switcher:打开快速切换": false,
      "graph:查看关系图谱": false,
      "canvas:新建白板": false,
      "daily-notes:打开/创建今天的日记": false,
      "templates:插入模板": false,
      "command-palette:打开命令面板": false,
      "templater-obsidian:Templater": false
    }
  },
  "active": "7e23daa8b7702666",
  "lastOpenFiles": [
    "source/_posts/视频播放器组件折腾记录.md",
    "未命名.canvas",
    "未命名 1.canvas",
    "source/_posts/nvm启动速度优化.md",
    "source/_posts/编译JDK8历史版本.md",
    "source/_posts/Java字节码和JDK版本对应.md",
    "source/_posts/iOS开发.md",
    "source/_posts/Golang-替换不可用包为私有仓库.md",
    "source/_posts/Android-远程镜像.md",
    "source/_posts/Windows-使用MiniGit.md",
    "source/_posts/Android-应用抓包实践.md",
    "source/_posts/开源生产力工具.md",
    "source/_posts/二进制编辑器.md",
    "source/_posts/二进制格式解析.md",
    "source/_posts/如何实现一门语言.md",
    "source/_posts/Android-Material3组件使用.md",
    "source/_posts/折腾GithubPages-Hexo-NexT.md",
    "source/_posts/Android-Smali调试.md",
    "source/_posts/RIME-折腾笔记.md",
    "source/_posts/npm-link的替代品slink.md",
    "source/_posts/Chrome-插件开发.md",
    "source/_posts/DiscordBot-开发资料.md",
    "source/_posts/JVM系统监控.md",
    "source/_posts/持续集成服务.md",
    "source/_posts/ADB架构学习.md",
    "编译Qt5.6.3-PENDING.md",
    "source/_posts/开发工具收集.md",
    "Pasted image 20240403160416.png",
    "node_modules/@next-theme/utils/node_modules/highlight.js/lib/languages/properties.js",
    "node_modules/@next-theme/utils/node_modules/highlight.js/lib/languages/powershell.js",
    "node_modules/@next-theme/utils/node_modules/highlight.js/lib/languages/prolog.js",
    "node_modules/@next-theme/utils/node_modules/highlight.js/lib/languages/plaintext.js",
    "node_modules/@next-theme/utils/node_modules/highlight.js/lib/languages/pony.js",
    "node_modules/@next-theme/utils/node_modules/highlight.js/lib/languages/pgsql.js",
    "node_modules/@next-theme/utils/node_modules/highlight.js/lib/languages/php-template.js",
    "node_modules/@next-theme/utils/node_modules/highlight.js/lib/languages/pf.js",
    "node_modules/@next-theme/utils/node_modules/highlight.js/lib/languages/parser3.js",
    "node_modules/@next-theme/utils/node_modules/highlight.js/lib/languages/php.js",
    "node_modules/@next-theme/utils/node_modules/highlight.js/styles/school-book.png",
    "node_modules/@next-theme/utils/node_modules/highlight.js/styles/pojoaque.jpg",
    "node_modules/@next-theme/utils/node_modules/highlight.js/styles/brown-papersq.png",
    "node_modules/@next-theme/utils/node_modules/highlight.js/scss/school-book.png",
    "node_modules/@next-theme/utils/node_modules/highlight.js/scss/pojoaque.jpg",
    "node_modules/@next-theme/utils/node_modules/highlight.js/scss/brown-papersq.png"
  ]
}